README.md
setup.py
reciprocalblast/__init__.py
reciprocalblast/db.py
reciprocalblast/match.py
reciprocalblast/search.py
reciprocalblast.egg-info/PKG-INFO
reciprocalblast.egg-info/SOURCES.txt
reciprocalblast.egg-info/dependency_links.txt
reciprocalblast.egg-info/top_level.txt