Metadata-Version: 1.1
Name: reciprocalblast
Version: 0.1.0
Summary: Perform reciprocal blastn analysis
Home-page: UNKNOWN
Author: Kent Kawashima
Author-email: kentkawashima@gmail.com
License: UNKNOWN
Keywords: blast,search,sequence,dna,bioinformatics
Platform: UNKNOWN
Classifier: Programming Language :: Python :: 3
Classifier: License :: OSI Approved :: MIT License
Classifier: Operating System :: OS Independent
